pylockgen/__init__.py
pylockgen/generator.py
pylockgen/security.py
pylockgen/strength.py
pylockgen-1.6.7.dist-info/LICENSE
pylockgen-1.6.7.dist-info/METADATA
pylockgen-1.6.7.dist-info/WHEEL
pylockgen-1.6.7.dist-info/top_level.txt
pylockgen-1.6.7.dist-info/RECORD
