Metadata-Version: 2.1
Name: pylockgen
Version: 1.6.7
Summary: Secure password generator and strength checker
Home-page: https://github.com/unknownmeovo/pylockgen
Author: Hadi Reza
Author-email: hadiraza.9002@gmail.com
License: MIT
Project-URL: Bug Tracker, https://github.com/unknownmeovo/pylockgen/issues
Platform: UNKNOWN
Classifier: Programming Language :: Python :: 3
Classifier: License :: OSI Approved :: MIT License
Classifier: Operating System :: OS Independent
Classifier: Topic :: Security
Classifier: Topic :: Utilities
Requires-Python: >=3.6
